ComplexExtension/__init__.py
ComplexExtension/complex_extension.py
ComplexExtension/main.py
ComplexExtension-1.0.1.dist-info/LICENSE
ComplexExtension-1.0.1.dist-info/METADATA
ComplexExtension-1.0.1.dist-info/WHEEL
ComplexExtension-1.0.1.dist-info/top_level.txt
ComplexExtension-1.0.1.dist-info/RECORD
